src/__init__.py
src/parse_notes_local.py
chat_notes-0.1.3.dist-info/METADATA
chat_notes-0.1.3.dist-info/WHEEL
chat_notes-0.1.3.dist-info/entry_points.txt
chat_notes-0.1.3.dist-info/top_level.txt
chat_notes-0.1.3.dist-info/RECORD
